oasis/VERSION.py
oasis/__init__.py
oasis/base.py
oasis/compatible/__init__.py
oasis/compatible/langchain.py
oasis/compatible/sdk.py
oasis/config.py
oasis/core/__init__.py
oasis/core/client_factory.py
oasis/core/context.py
oasis/core/transports.py
oasis/core/types.py
oasis/errors.py
oasis/utils.py
oasis_sdk-0.1.8.dist-info/METADATA
oasis_sdk-0.1.8.dist-info/WHEEL
oasis_sdk-0.1.8.dist-info/licenses/LICENSE
oasis_sdk-0.1.8.dist-info/RECORD
