Metadata-Version: 2.4
Name: oasis-sdk
Version: 0.1.8
Summary: Oasis LLM Proxy Client
License-File: LICENSE
Author: 신강식 / AI솔루션팀
Author-email: kangsik.shin@hanwha.com
Requires-Python: >=3.11,<4.0
Classifier: Programming Language :: Python :: 3
Classifier: Programming Language :: Python :: 3.11
Classifier: Programming Language :: Python :: 3.12
Classifier: Programming Language :: Python :: 3.13
Classifier: Programming Language :: Python :: 3.14
Requires-Dist: langchain-openai (>=0.3.28,<1.0.0)
Requires-Dist: openai (>=2.0.0,<3.0.0)
